git_diff_lm/__init__.py
git_diff_lm/main.py
komitai-0.0.2.dist-info/METADATA
komitai-0.0.2.dist-info/WHEEL
komitai-0.0.2.dist-info/entry_points.txt
komitai-0.0.2.dist-info/top_level.txt
komitai-0.0.2.dist-info/RECORD
