Metadata-Version: 2.1
Name: komitai
Version: 0.0.2
Summary: Generate git commit using AI
Author-email: Angga <anggakawa@gmail.com>
Project-URL: Homepage, https://github.com/anggakawa/git-diff-lm
Project-URL: Issues, https://github.com/anggakawa/git-diff-lm/issues
Classifier: Programming Language :: Python :: 3
Classifier: License :: OSI Approved :: MIT License
Classifier: Operating System :: OS Independent
Requires-Python: >=3.6
Requires-Dist: annotated-types>=0.7.0
Requires-Dist: anyio>=4.7.0
Requires-Dist: certifi>=2024.12.14
Requires-Dist: colorama>=0.4.6
Requires-Dist: distro>=1.9.0
Requires-Dist: exceptiongroup>=1.2.2
Requires-Dist: h11>=0.14.0
Requires-Dist: httpcore>=1.0.7
Requires-Dist: httpx>=0.28.1
Requires-Dist: idna>=3.10
Requires-Dist: jiter>=0.8.2
Requires-Dist: openai>=1.58.1
Requires-Dist: prompt_toolkit>=3.0.48
Requires-Dist: pydantic>=2.6.1
Requires-Dist: pydantic_core>=2.21.0
Requires-Dist: python-dotenv>=1.0.1
Requires-Dist: sniffio>=1.3.1
Requires-Dist: tqdm>=4.67.1
Requires-Dist: typing_extensions>=4.12.2
Requires-Dist: wcwidth>=0.2.13
